gradio_doctestcode/__init__.py
gradio_doctestcode/doctestcode.py
gradio_doctestcode/doctestcode.pyi
gradio_doctestcode/templates/component/Index-099f09d5.js
gradio_doctestcode/templates/component/dockerfile-1dc69d82.js
gradio_doctestcode/templates/component/frontmatter-6cbbd4b8.js
gradio_doctestcode/templates/component/index-1be0e1ec.js
gradio_doctestcode/templates/component/index-2a98de91.js
gradio_doctestcode/templates/component/index-8a77c6db.js
gradio_doctestcode/templates/component/index-94b5b93a.js
gradio_doctestcode/templates/component/index-df25bc8b.js
gradio_doctestcode/templates/component/index-e69dc063.js
gradio_doctestcode/templates/component/index-f107f569.js
gradio_doctestcode/templates/component/index.js
gradio_doctestcode/templates/component/r-1df568be.js
gradio_doctestcode/templates/component/shell-9b920301.js
gradio_doctestcode/templates/component/style.css
gradio_doctestcode/templates/component/yaml-cef3802d.js
gradio_doctestcode/templates/example/index.js
gradio_doctestcode/templates/example/style.css
gradio_doctestcode-0.0.4.dist-info/METADATA
gradio_doctestcode-0.0.4.dist-info/WHEEL
gradio_doctestcode-0.0.4.dist-info/RECORD
